{
  "schema_version": "5.3",
  "host_arch_pair": "linux/amd64",
  "environment": {
    "kernel_sysctls_applied": [],
    "loadgen_host": "msa2-client",
    "fabric": "3-host Tailscale overlay"
  },
  "benchmark_config": {
    "started_at": "0001-01-01T00:00:00Z",
    "finished_at": "2026-06-09T04:19:49.846685Z",
    "runs": 1,
    "duration": 40000000000,
    "warmup": 10000000000,
    "git_ref": "v1.4.15",
    "loadgen_version": "v1.4.7",
    "celeris_version": "v1.4.15",
    "scenarios_filter": "target=msa2-server"
  },
  "benchmarks": [
    {
      "name": "actix-web",
      "category": "rust-actix",
      "language": "rust",
      "language_version": "",
      "framework": "actix-web",
      "framework_version": "",
      "engine": "h1",
      "compile_options": [
        "profile=release-fat",
        "RUSTFLAGS=-C target-cpu=native"
      ],
      "saturation_mode_rps": {
        "get-json": 701705.9026982517,
        "get-json-1k": 632128.4953792288,
        "get-json-64k": 35762.34615707768,
        "get-simple": 691102.5909306934,
        "get-simple-1024c": 686943.784655719,
        "get-simple-128c": 689583.490297265,
        "post-4k": 481021.52568757103,
        "post-64k": 35797.079578896526
      },
      "rated_mode_p99_at_target_rps": {},
      "latency_at_slo": {},
      "hdr_histogram_b64": {},
      "loadgen_cpu_p95": {},
      "sent_vs_handled_delta_pct": {
        "get-json": 0.00017811759765528845,
        "get-json-1k": 0.00018190379883148165,
        "get-json-64k": 0.0644452847649809,
        "get-simple": 0.00038339894157296724,
        "get-simple-1024c": 0.00029110867501668235,
        "get-simple-128c": 0.00011599798960984258,
        "post-4k": 0.0025100147249000476,
        "post-64k": 0.007820671991240848
      }
    },
    {
      "name": "aspnet",
      "category": "dotnet-aspnetcore",
      "language": "csharp",
      "language_version": "",
      "framework": "aspnet",
      "framework_version": "",
      "engine": "h1",
      "compile_options": [],
      "saturation_mode_rps": {
        "get-json": 639560.5369380518,
        "get-json-1k": 581294.9384651585,
        "get-json-64k": 35713.63563707474,
        "get-simple": 617815.56389356,
        "get-simple-1024c": 621999.3526380587,
        "get-simple-128c": 627812.3488972966,
        "post-4k": 401265.48948977544,
        "post-64k": 35717.101629264
      },
      "rated_mode_p99_at_target_rps": {},
      "latency_at_slo": {},
      "hdr_histogram_b64": {},
      "loadgen_cpu_p95": {},
      "sent_vs_handled_delta_pct": {}
    },
    {
      "name": "axum",
      "category": "rust-tower",
      "language": "rust",
      "language_version": "",
      "framework": "axum",
      "framework_version": "",
      "engine": "h1",
      "compile_options": [
        "profile=release-fat",
        "RUSTFLAGS=-C target-cpu=native"
      ],
      "saturation_mode_rps": {
        "get-json": 613248.0474499812,
        "get-json-1k": 571176.5356236418,
        "get-json-64k": 35755.57108848379,
        "get-simple": 612474.1361259503,
        "get-simple-1024c": 608748.9741121802,
        "get-simple-128c": 609092.1833955998,
        "post-4k": 433946.09358789644,
        "post-64k": 35766.75495625906
      },
      "rated_mode_p99_at_target_rps": {},
      "latency_at_slo": {},
      "hdr_histogram_b64": {},
      "loadgen_cpu_p95": {},
      "sent_vs_handled_delta_pct": {}
    },
    {
      "name": "celeris-epoll-h1-sync",
      "category": "celeris",
      "language": "go",
      "language_version": "go1.26.4",
      "framework": "celeris",
      "framework_version": "",
      "engine": "epoll-h1-sync",
      "compile_options": [
        "CGO_ENABLED=0",
        "GOAMD64=v3",
        "trimpath",
        "ldflags=-s -w"
      ],
      "saturation_mode_rps": {
        "chain-fullstack-get-json": 591439.5897269723,
        "get-json": 694034.2018937543,
        "get-json-1k": 618075.1855965327,
        "get-json-64k": 35770.57763235717,
        "get-simple": 706263.1242914994,
        "get-simple-1024c": 681458.2985751667,
        "get-simple-128c": 689106.0602801242,
        "post-4k": 453039.17224420764,
        "post-64k": 35789.299489827245,
        "sse-fanout-128": 61182.71058181371,
        "ws-echo": 549876.7431259514
      },
      "rated_mode_p99_at_target_rps": {},
      "latency_at_slo": {},
      "hdr_histogram_b64": {},
      "loadgen_cpu_p95": {},
      "sent_vs_handled_delta_pct": {}
    },
    {
      "name": "celeris-iouring-auto+upg-async",
      "category": "celeris",
      "language": "go",
      "language_version": "go1.26.4",
      "framework": "celeris",
      "framework_version": "",
      "engine": "iouring-auto+upg-async",
      "compile_options": [
        "CGO_ENABLED=0",
        "GOAMD64=v3",
        "trimpath",
        "ldflags=-s -w"
      ],
      "saturation_mode_rps": {
        "auto-mix-111": 672803.9834370456,
        "chain-fullstack-get-json": 528234.5778927002,
        "get-json": 605014.8158327552,
        "get-json-1k": 562757.4670245901,
        "get-json-64k": 35739.81002382183,
        "get-simple": 604899.0648091161,
        "get-simple-1024c": 600576.0843148794,
        "get-simple-128c": 605346.587739075,
        "post-4k": 443724.6809097235,
        "post-64k": 35796.80501309026,
        "sse-fanout-128": 60287.61518466536,
        "ws-echo": 532262.4562896843
      },
      "rated_mode_p99_at_target_rps": {},
      "latency_at_slo": {},
      "hdr_histogram_b64": {},
      "loadgen_cpu_p95": {},
      "sent_vs_handled_delta_pct": {
        "auto-mix-111": 0.0000037156877600563416
      }
    },
    {
      "name": "celeris-iouring-h1-async",
      "category": "celeris",
      "language": "go",
      "language_version": "go1.26.4",
      "framework": "celeris",
      "framework_version": "",
      "engine": "iouring-h1-async",
      "compile_options": [
        "CGO_ENABLED=0",
        "GOAMD64=v3",
        "trimpath",
        "ldflags=-s -w"
      ],
      "saturation_mode_rps": {
        "chain-fullstack-get-json": 465900.78746922605,
        "get-json": 601441.4640473963,
        "get-json-1k": 557451.3352713846,
        "get-json-64k": 35754.33345919868,
        "get-simple": 604631.419696408,
        "get-simple-1024c": 603748.2528797431,
        "get-simple-128c": 606456.4884967406,
        "post-4k": 430626.804746992,
        "post-64k": 35799.06477794532,
        "sse-fanout-128": 60915.25817592584,
        "ws-echo": 524565.5884206182
      },
      "rated_mode_p99_at_target_rps": {},
      "latency_at_slo": {},
      "hdr_histogram_b64": {},
      "loadgen_cpu_p95": {},
      "sent_vs_handled_delta_pct": {
        "chain-fullstack-get-json": 0.000005365267404927461
      }
    },
    {
      "name": "celeris-std-h1",
      "category": "celeris",
      "language": "go",
      "language_version": "go1.26.4",
      "framework": "celeris",
      "framework_version": "",
      "engine": "std-h1",
      "compile_options": [
        "CGO_ENABLED=0",
        "GOAMD64=v3",
        "trimpath",
        "ldflags=-s -w"
      ],
      "saturation_mode_rps": {
        "chain-fullstack-get-json": 147125.53689049356,
        "get-json": 301590.64605203597,
        "get-json-1k": 312315.92633936787,
        "get-json-64k": 35682.5051137507,
        "get-simple": 321089.4603839895,
        "get-simple-1024c": 323513.2497016064,
        "get-simple-128c": 321322.2164722159,
        "post-4k": 131339.6466916201,
        "post-64k": 35767.621283918656,
        "sse-fanout-128": 60663.627811607075,
        "ws-echo": 578096.0438290744
      },
      "rated_mode_p99_at_target_rps": {},
      "latency_at_slo": {},
      "hdr_histogram_b64": {},
      "loadgen_cpu_p95": {},
      "sent_vs_handled_delta_pct": {
        "chain-fullstack-get-json": 0.0031770653260696897,
        "get-json": 0.0012598071218720005,
        "get-json-1k": 0.0007763437028841408,
        "get-json-64k": 0.08567509593789362,
        "get-simple": 0.0020474132646066782,
        "get-simple-1024c": 0.0005485855995198408,
        "get-simple-128c": 0.0013302466425080392,
        "post-4k": 0.003616043203722926,
        "post-64k": 0.007827197835220713,
        "sse-fanout-128": 0.0026371394947900012
      }
    },
    {
      "name": "echo-h1",
      "category": "go-net-http",
      "language": "go",
      "language_version": "go1.26.4",
      "framework": "echo",
      "framework_version": "",
      "engine": "h1",
      "compile_options": [
        "CGO_ENABLED=0",
        "GOAMD64=v3",
        "trimpath",
        "ldflags=-s -w"
      ],
      "saturation_mode_rps": {
        "chain-fullstack-get-json": 144122.6764190124,
        "get-json": 389579.37778830965,
        "get-json-1k": 395132.7878165841,
        "get-json-64k": 35717.64938858456,
        "get-simple": 409998.5471604205,
        "get-simple-1024c": 408612.4202803664,
        "get-simple-128c": 409602.8102606192,
        "post-4k": 347613.26586701116,
        "post-64k": 35788.31260256084
      },
      "rated_mode_p99_at_target_rps": {},
      "latency_at_slo": {},
      "hdr_histogram_b64": {},
      "loadgen_cpu_p95": {},
      "sent_vs_handled_delta_pct": {}
    },
    {
      "name": "fasthttp-h1",
      "category": "go-fasthttp",
      "language": "go",
      "language_version": "go1.26.4",
      "framework": "fasthttp",
      "framework_version": "",
      "engine": "h1",
      "compile_options": [
        "CGO_ENABLED=0",
        "GOAMD64=v3",
        "trimpath",
        "ldflags=-s -w"
      ],
      "saturation_mode_rps": {
        "chain-fullstack-get-json": 588760.9249966763,
        "get-json": 595950.9183376761,
        "get-json-1k": 567211.5742550025,
        "get-json-64k": 35678.537850982066,
        "get-simple": 595240.2038604259,
        "get-simple-1024c": 590934.8017742481,
        "get-simple-128c": 588818.9400019891,
        "post-4k": 435273.2600320715,
        "post-64k": 35801.68554836489
      },
      "rated_mode_p99_at_target_rps": {},
      "latency_at_slo": {},
      "hdr_histogram_b64": {},
      "loadgen_cpu_p95": {},
      "sent_vs_handled_delta_pct": {}
    },
    {
      "name": "fiber-h1",
      "category": "go-fasthttp",
      "language": "go",
      "language_version": "go1.26.4",
      "framework": "fiber",
      "framework_version": "",
      "engine": "h1",
      "compile_options": [
        "CGO_ENABLED=0",
        "GOAMD64=v3",
        "trimpath",
        "ldflags=-s -w"
      ],
      "saturation_mode_rps": {
        "chain-fullstack-get-json": 574661.1204885493,
        "get-json": 591408.6190909914,
        "get-json-1k": 564793.5894018043,
        "get-json-64k": 35693.72925845144,
        "get-simple": 601061.6740716991,
        "get-simple-1024c": 591415.785831094,
        "get-simple-128c": 601527.5967291057,
        "post-4k": 434109.0507776089,
        "post-64k": 35803.26686541154
      },
      "rated_mode_p99_at_target_rps": {},
      "latency_at_slo": {},
      "hdr_histogram_b64": {},
      "loadgen_cpu_p95": {},
      "sent_vs_handled_delta_pct": {}
    },
    {
      "name": "gin-h1",
      "category": "go-net-http",
      "language": "go",
      "language_version": "go1.26.4",
      "framework": "gin",
      "framework_version": "",
      "engine": "h1",
      "compile_options": [
        "CGO_ENABLED=0",
        "GOAMD64=v3",
        "trimpath",
        "ldflags=-s -w"
      ],
      "saturation_mode_rps": {
        "chain-fullstack-get-json": 147753.23405873025,
        "get-json": 392921.3796517675,
        "get-json-1k": 394281.3077898285,
        "get-json-64k": 34912.40367775726,
        "get-simple": 415613.00038832217,
        "get-simple-1024c": 414013.14761768695,
        "get-simple-128c": 413105.81634694966,
        "post-4k": 162198.99910354937,
        "post-64k": 35736.96440550801
      },
      "rated_mode_p99_at_target_rps": {},
      "latency_at_slo": {},
      "hdr_histogram_b64": {},
      "loadgen_cpu_p95": {},
      "sent_vs_handled_delta_pct": {}
    },
    {
      "name": "gnet-h1",
      "category": "go-gnet",
      "language": "go",
      "language_version": "go1.26.4",
      "framework": "gnet",
      "framework_version": "",
      "engine": "h1",
      "compile_options": [
        "CGO_ENABLED=0",
        "GOAMD64=v3",
        "trimpath",
        "ldflags=-s -w"
      ],
      "saturation_mode_rps": {
        "get-json": 716599.279977635,
        "get-json-1k": 647253.0662717064,
        "get-json-64k": 35788.60325225257,
        "get-simple": 711212.8036029377,
        "get-simple-1024c": 709354.0847418508,
        "get-simple-128c": 705865.8898531467,
        "post-4k": 466454.65575217997,
        "post-64k": 35801.16022363731
      },
      "rated_mode_p99_at_target_rps": {},
      "latency_at_slo": {},
      "hdr_histogram_b64": {},
      "loadgen_cpu_p95": {},
      "sent_vs_handled_delta_pct": {}
    },
    {
      "name": "hertz-h1",
      "category": "go-netpoll",
      "language": "go",
      "language_version": "go1.26.4",
      "framework": "hertz",
      "framework_version": "",
      "engine": "h1",
      "compile_options": [
        "CGO_ENABLED=0",
        "GOAMD64=v3",
        "trimpath",
        "ldflags=-s -w"
      ],
      "saturation_mode_rps": {
        "chain-fullstack-get-json": 431179.6264371526,
        "get-json": 455411.01434639003,
        "get-json-1k": 454234.9543285558,
        "get-json-64k": 35734.61610243593,
        "get-simple": 457404.7709720463,
        "get-simple-1024c": 456971.84507160913,
        "get-simple-128c": 457239.286970896,
        "post-4k": 208432.39264938075,
        "post-64k": 35819.6636580627
      },
      "rated_mode_p99_at_target_rps": {},
      "latency_at_slo": {},
      "hdr_histogram_b64": {},
      "loadgen_cpu_p95": {},
      "sent_vs_handled_delta_pct": {}
    },
    {
      "name": "hyper",
      "category": "rust-hyper",
      "language": "rust",
      "language_version": "",
      "framework": "hyper",
      "framework_version": "",
      "engine": "h1",
      "compile_options": [
        "profile=release-fat",
        "RUSTFLAGS=-C target-cpu=native"
      ],
      "saturation_mode_rps": {
        "get-json": 625494.946172233,
        "get-json-1k": 584449.6955558787,
        "get-json-64k": 35753.77681132221,
        "get-simple": 619644.66794167,
        "get-simple-1024c": 621414.7373158929,
        "get-simple-128c": 620932.9200340285,
        "post-4k": 429617.0018108952,
        "post-64k": 35780.45874251053
      },
      "rated_mode_p99_at_target_rps": {},
      "latency_at_slo": {},
      "hdr_histogram_b64": {},
      "loadgen_cpu_p95": {},
      "sent_vs_handled_delta_pct": {}
    },
    {
      "name": "stdhttp-h1",
      "category": "go-net-http",
      "language": "go",
      "language_version": "go1.26.4",
      "framework": "stdhttp",
      "framework_version": "",
      "engine": "h1",
      "compile_options": [
        "CGO_ENABLED=0",
        "GOAMD64=v3",
        "trimpath",
        "ldflags=-s -w"
      ],
      "saturation_mode_rps": {
        "chain-fullstack-get-json": 136545.35097890464,
        "get-json": 412854.8410494129,
        "get-json-1k": 400074.76832306094,
        "get-json-64k": 35400.49010026126,
        "get-simple": 417918.74083150516,
        "get-simple-1024c": 415423.1252109032,
        "get-simple-128c": 415032.2752754251,
        "post-4k": 349428.6659273062,
        "post-64k": 33942.75442759726
      },
      "rated_mode_p99_at_target_rps": {},
      "latency_at_slo": {},
      "hdr_histogram_b64": {},
      "loadgen_cpu_p95": {},
      "sent_vs_handled_delta_pct": {}
    }
  ]
}